README.rst
setup.py
Congresso.egg-info/PKG-INFO
Congresso.egg-info/SOURCES.txt
Congresso.egg-info/dependency_links.txt
Congresso.egg-info/top_level.txt
congresso/__init__.py
congresso/connection.py
congresso/utils.py
congresso/camara/__init__.py
congresso/camara/deputados.py
congresso/camara/orgaos.py
congresso/camara/proposicoes.py
congresso/camara/sessoesreunioes.py