Metadata-Version: 1.0
Name: Congresso
Version: 0.1.3
Summary: Low Level Python Client of Brazilian Camara e Senado Federal API
Home-page: https://github.com/CongressoEmNumeros/congresso
Author: Joao Carabetta
Author-email: joao.carabetta@gmail.com
License: APACHE
Platform: UNKNOWN
